channels_oneway/__init__.py
channels_oneway/__version__.py
channels_oneway/bindings.py
channels_oneway/mixins.py
channels_oneway/utils.py
drf_channels_oneway_ws-0.3.0.dist-info/LICENSE
drf_channels_oneway_ws-0.3.0.dist-info/METADATA
drf_channels_oneway_ws-0.3.0.dist-info/WHEEL
drf_channels_oneway_ws-0.3.0.dist-info/top_level.txt
drf_channels_oneway_ws-0.3.0.dist-info/RECORD
