Metadata-Version: 2.1
Name: drf-channels-oneway-ws
Version: 0.3.0
Summary: Simple one-way bindings for django-channels with some specific support for django-rest-framework serializers and websockets. I.e. enrich your existing API with push notifications.
Home-page: https://github.com/evocount/drf-channels-oneway-ws
Author: Till Theato
Author-email: till.theato@evocount.de
License: MIT
Platform: UNKNOWN
Classifier: Development Status :: 4 - Beta
Classifier: Intended Audience :: Developers
Classifier: License :: OSI Approved :: MIT License
Classifier: Programming Language :: Python
Classifier: Programming Language :: Python :: 3
Classifier: Programming Language :: Python :: 3.6
Classifier: Programming Language :: Python :: Implementation :: CPython
Classifier: Programming Language :: Python :: Implementation :: PyPy
Requires-Python: >=3.6.0
Requires-Dist: Django
Requires-Dist: channels
Requires-Dist: djangorestframework
Provides-Extra: test
Requires-Dist: pytest ; extra == 'test'
Requires-Dist: pytest-cov ; extra == 'test'
Requires-Dist: pytest-django ; extra == 'test'
Requires-Dist: pytest-asyncio ; extra == 'test'
